django_lms_geotool/__init__.py
django_lms_geotool/admin.py
django_lms_geotool/apps.py
django_lms_geotool/models.py
django_lms_geotool/tests.py
django_lms_geotool/urls.py
django_lms_geotool/views.py
django_lms_geotool/migrations/__init__.py
django_lms_geotool/static/django_lms_geotool/css/lib/element-plus.css
django_lms_geotool/static/django_lms_geotool/js/lib/element/dayjs.min.js
django_lms_geotool/static/django_lms_geotool/js/lib/element/element-plus.min.js
django_lms_geotool/static/django_lms_geotool/js/lib/element/zh-cn.js
django_lms_geotool/static/django_lms_geotool/js/lib/vue/vue.global.prod.js
django_lms_geotool/templates/common.html
django_lms_geotool/templates/django_lms_geotool/convert.html
django_lms_geotool/templates/django_lms_geotool/dimsum.html
django_lms_geotool/templates/django_lms_geotool/matrix.html
django_lms_geotool/templates/django_lms_geotool/translation.html
django_lms_geotool/tools/__init__.py
django_lms_geotool/tools/geographic.py
django_lms_geotool/tools/matrix.py
django_lms_geotool/tools/projected.py
django_lms_geotool-0.7.0.dist-info/licenses/LICENSE
django_lms_geotool-0.7.0.dist-info/METADATA
django_lms_geotool-0.7.0.dist-info/WHEEL
django_lms_geotool-0.7.0.dist-info/top_level.txt
django_lms_geotool-0.7.0.dist-info/RECORD
