Metadata-Version: 2.4
Name: django-lms-geotool
Version: 0.7.0
Summary: LMS的地理信息工具集
Home-page: https://github.com/cuscri/geotool
Author: MrYuGoui
Author-email: MrYuGoui@163.com
License: MIT
Classifier: Programming Language :: Python :: 3
Classifier: License :: OSI Approved :: MIT License
Classifier: Operating System :: OS Independent
Requires-Python: >=3.6
License-File: LICENSE
Requires-Dist: Django
Requires-Dist: numpy
Requires-Dist: django-simpleui
Requires-Dist: djangorestframework
Requires-Dist: django-import-export
Dynamic: author
Dynamic: author-email
Dynamic: classifier
Dynamic: description
Dynamic: description-content-type
Dynamic: home-page
Dynamic: license
Dynamic: license-file
Dynamic: requires-dist
Dynamic: requires-python
Dynamic: summary
